retinalysis_registration-0.1.4.dist-info/licenses/LICENCE
rtnls_registration/__init__.py
rtnls_registration/_version.py
rtnls_registration/cfi_bounds.py
rtnls_registration/circle_fit.py
rtnls_registration/evaluation.py
rtnls_registration/mask_extraction.py
rtnls_registration/preprocess.py
rtnls_registration/registration.py
rtnls_registration/registration_fire905.py
rtnls_registration/robust_affine.py
rtnls_registration/timing.py
rtnls_registration/transformation.py
rtnls_registration/utils.py
retinalysis_registration-0.1.4.dist-info/METADATA
retinalysis_registration-0.1.4.dist-info/WHEEL
retinalysis_registration-0.1.4.dist-info/top_level.txt
retinalysis_registration-0.1.4.dist-info/RECORD
