Metadata-Version: 2.4
Name: retinalysis-registration
Version: 0.1.4
Summary: Easy, robust registration of retinal images
Author-email: Bart Liefers <b.liefers@erasmusmc.nl>
License:                     GNU AFFERO GENERAL PUBLIC LICENSE
Project-URL: Homepage, https://github.com/Eyened/retinalysis-registration
Project-URL: Bug Tracker, https://github.com/Eyened/retinalysis-registration/issues
Classifier: License :: OSI Approved :: GNU Affero General Public License v3 or later (AGPLv3+)
Classifier: Programming Language :: Python :: 3
Classifier: Programming Language :: Python :: 3.9
Classifier: Programming Language :: Python :: 3.10
Classifier: Programming Language :: Python :: 3.11
Classifier: Programming Language :: Python :: 3.12
Classifier: Operating System :: OS Independent
Classifier: Intended Audience :: Science/Research
Classifier: Topic :: Scientific/Engineering :: Image Processing
Requires-Python: >=3.9
License-File: LICENCE
Requires-Dist: numpy==2.*
Requires-Dist: scikit-learn==1.*
Requires-Dist: scikit-image==0.24.*
Requires-Dist: scipy==1.*
Requires-Dist: pydicom<4,>=3
Requires-Dist: opencv-python-headless==4.*
Requires-Dist: matplotlib==3.*
Requires-Dist: Pillow==11.*
Dynamic: license-file
